[
  {
    "id": 1,
    "date": "2026-04-02",
    "title": "知足不辱，知止不殆",
    "source": "《道德经》第四十四章",
    "body": "知道满足就不会受辱，知道适可而止就不会陷于危险。\n\n### 应用\n\n巴菲特说\"别人贪婪我恐惧\"——本质上就是这个道理。\n\n- **牛市疯狂时**：懂得止盈，落袋为安\n- **熊市恐慌时**：懂得定投，收集筹码\n- 真正的高手不是赚最多的人，而是活得最久的人\n\n> 不懂止损的人，迟早被市场教育；不懂止盈的人，迟早把利润还给市场。",
    "tags": ["道德经", "投资", "哲学"]
  },
  {
    "id": 2,
    "date": "2026-04-03",
    "title": "兵者，诡道也",
    "source": "《孙子兵法》始计篇",
    "body": "战争的本质是欺骗。能打却装作不能打，想打却装作不想打，近处却示远，远处却示近。\n\n### 应用\n\n特朗普对伊朗的打击——先谈判、后突袭，正是「诡道」的现代演绎。\n\n- 谈判桌上的姿态，往往是战场的掩护\n- **看似和平的姿态，可能正是进攻的前兆**\n\n> 高手从不让对方看清真实意图，战争还没开始，胜负已在欺骗中决定。",
    "tags": ["孙子兵法", "战争", "策略"]
  },
  {
    "id": 3,
    "date": "2026-04-03",
    "title": "美伊冲突：大国博弈的胜利宣言",
    "source": "时事热点",
    "body": "美国对伊朗核设施发动军事打击，持续32天后特朗普宣布「伊朗不再构成威胁」。但「不再构成威胁」是政治表态，不是事实判断。\n\n### 局势判断\n\n美方目标已达成（核设施被毁），但伊朗报复能力仍存。「不再构成威胁」是政治表态，不是事实判断。后续风险：伊朗代理人可能持续骚扰。\n\n### 普通人应对\n\n**石油/能源**\n\n- 油价短期波动已过，现在不是入场时机\n- 如果想对冲，5-10% 黄金ETF（GLD）足够\n\n**投资组合**\n\n- 检查是否有中东相关资产\n- 比例超过20%建议减仓分散\n\n**不做也OK**\n\n如果你不持有中东资产、不炒能源股，这件事对你的财务影响接近零，不用焦虑。\n\n> 大国博弈的胜利宣言听听就好，普通人最优策略是：不押注、不恐慌、等尘埃落定再决策。",
    "tags": ["时事热点", "美伊冲突", "投资"]
  },
  {
    "id": 21,
    "date": "2026-04-04",
    "title": "知行合一",
    "source": "王阳明心学",
    "body": "知道却不去做，等于不知道。真正的知识，必须体现在行动中。\n\n### 应用\n\n**学习陷阱**\n\n- 看了100本书却不实践 = 0\n- 知道健身好处却不去健身 = 不知道\n- 懂得投资原理却不敢下手 = 没懂\n\n**破局方法**\n\n- 学一个，做一个，再学下一个\n- 小步快跑，边做边学\n- 行动中修正认知\n\n**直接行动**\n\n- 今天学到的东西，立刻找一个场景试用\n- 设定\"24小时实践规则\"：学到就做，不拖延\n\n**不做也OK**\n\n- 如果你已经在实践中学习，恭喜你已经在知行合一的路上\n\n> 知而不行，只是未知。真正的知识，长在行动里。",
    "tags": ["王阳明", "心学", "行动"]
  },
  {
    "id": 22,
    "date": "2026-04-04",
    "title": "查理·芒格：多元思维模型",
    "source": "投资大师思想",
    "body": "芒格认为，单一学科的知识是危险的。真正的智慧来自跨学科的思维模型。\n\n### 核心思想\n\n**100个思维模型**\n\n- 物理学：临界质量、复利效应\n- 生物学：进化论、适者生存\n- 心理学：激励机制、认知偏误\n- 经济学：机会成本、边际效应\n\n### 应用\n\n**投资决策**\n\n- 不只看财报（会计学）\n- 还要看护城河（经济学）\n- 分析管理层激励（心理学）\n- 理解行业周期（历史学）\n\n**职业发展**\n\n- 不只精通本专业\n- 还要懂商业、心理、沟通\n- T型人才：一专多能\n\n**直接行动**\n\n- 每月学习一个新领域的基础概念\n- 用不同学科的视角分析同一个问题\n\n**不做也OK**\n\n- 如果你的工作不需要复杂决策，专注单一技能也很好\n\n> 要想变聪明，唯一的办法是不断学习。但如果只学一个学科，你会变成一个拿着锤子的人，看什么都像钉子。",
    "tags": ["芒格", "投资", "思维模型"]
  }
]